wsgiserver.py
WSGIserver-1.3.dist-info/metadata.json
WSGIserver-1.3.dist-info/top_level.txt
WSGIserver-1.3.dist-info/METADATA
WSGIserver-1.3.dist-info/DESCRIPTION.rst
WSGIserver-1.3.dist-info/RECORD
WSGIserver-1.3.dist-info/WHEEL
